rootbridge/Facebook.py
rootbridge/GitHub.py
rootbridge/Twitter.py
rootbridge/__init__.py
rootbridge-0.0.2.dist-info/LICENSE
rootbridge-0.0.2.dist-info/WHEEL
rootbridge-0.0.2.dist-info/METADATA
rootbridge-0.0.2.dist-info/RECORD
